<?xml version="1.0" encoding="utf-8"?>
    <Patch>
        <Operation Class="PatchOperationAdd">
            <xpath>Defs/RecipeDef[defName="MakeAmmo_MusketBall"]</xpath>
                <value>
                    <researchPrerequisite>CE_Gunpowder</researchPrerequisite>
                </value>
        </Operation>
        
        <Operation Class="PatchOperationAdd">
            <xpath>Defs/RecipeDef[defName="MakeAmmo_BlunderbussShot"]</xpath>
                <value>
                    <researchPrerequisite>CE_Gunpowder</researchPrerequisite>
                </value>
        </Operation>

        <Operation Class="PatchOperationAdd">
            <xpath>Defs/RecipeDef[defName="MakeAmmo_44Magnum_HP"]</xpath>
                <value>
                    <researchPrerequisite>CEH_Revolver_Research</researchPrerequisite>
                </value>
        </Operation>
        
        <Operation Class="PatchOperationAdd">
            <xpath>Defs/RecipeDef[defName="MakeAmmo_44Magnum_FMJ"]</xpath>
                <value>
                    <researchPrerequisite>CEH_44_FMJ_Research</researchPrerequisite>
                </value>
        </Operation>
    
        <Operation Class="PatchOperationAdd">
            <xpath>Defs/RecipeDef[defName="MakeAmmo_44Magnum_AP"]</xpath>
                <value>
                    <researchPrerequisite>CEH_44_AP_Research</researchPrerequisite>
                </value>
        </Operation>

        <Operation Class="PatchOperationAdd">
            <xpath>Defs/RecipeDef[defName="MakeAmmo_45ACP_HP"]</xpath>
                <value>
                    <researchPrerequisite>CEH_AutoPistol_Research</researchPrerequisite>
                </value>
        </Operation>
    
        <Operation Class="PatchOperationAdd">
            <xpath>Defs/RecipeDef[defName="MakeAmmo_45ACP_FMJ"]</xpath>
                <value>
                    <researchPrerequisite>CEH_45ACP_FMJ_Research</researchPrerequisite>
                </value>
        </Operation>
    
        <Operation Class="PatchOperationAdd">
            <xpath>Defs/RecipeDef[defName="MakeAmmo_45ACP_AP"]</xpath>
                <value>
                    <researchPrerequisite>CEH_45ACP_AP_Research</researchPrerequisite>
                </value>
        </Operation>

        <Operation Class="PatchOperationAdd">
            <xpath>Defs/RecipeDef[defName="MakeAmmo_303British_HP"]</xpath>
                <value>
                    <researchPrerequisite>CEH_BoltActionRifles_Research</researchPrerequisite>
                </value>
        </Operation>

        <Operation Class="PatchOperationFindMod">
            <mods>
                <li>Combat Extended Guns</li>
            </mods>
            <match Class="PatchOperationSequence">
                <operations>
                    
                </operations>
            </match>
        </Operation>

        <Operation Class="PatchOperationFindMod">
            <mods>
                <li>Combat Extended Armory</li>
            </mods>
            <match Class="PatchOperationSequence">
                <operations>
                    <li Class="PatchOperationAdd">
                        <xpath>Defs/RecipeDef[
                            defName="MakeAmmo_9x19mmPara_HP"
                            ]</xpath>
                            <value>
                                <researchPrerequisite>CEH_MachinePistol_Research</researchPrerequisite>
                            </value>
                    </li>
    
                    <li Class="PatchOperationAdd">
                        <xpath>Defs/RecipeDef[
                            defName="MakeAmmo_9x19mmPara_FMJ"
                            ]</xpath>
                            <value>
                                <researchPrerequisite>CEH_9x19FMJ_Research</researchPrerequisite>
                            </value>
                    </li>
    
                    <li Class="PatchOperationAdd">
                        <xpath>Defs/RecipeDef[
                            defName="MakeAmmo_9x19mmPara_AP"
                            ]</xpath>
                            <value>
                                <researchPrerequisite>CEH_9x19AP_Research</researchPrerequisite>
                            </value>
                    </li>
    
                    <li Class="PatchOperationAdd">
                        <xpath>Defs/RecipeDef[
                            defName="MakeAmmo_762x54mmR_HP"
                            ]</xpath>
                            <value>
                                <researchPrerequisite>CEH_BoltActionRifles_Research</researchPrerequisite>
                            </value>
                    </li>
    
                    <li Class="PatchOperationAdd">
                        <xpath>Defs/RecipeDef[
                            defName="MakeAmmo_45Colt_HP" or
                            defName="MakeAmmo_4570Gov_HP"
                            ]</xpath>
                            <value>
                                <researchPrerequisite>CEH_LeverActionRifles_Research</researchPrerequisite>
                            </value>
                    </li>
    
                    <li Class="PatchOperationAdd">
                        <xpath>Defs/RecipeDef[
                            defName="MakeAmmo_45Colt_FMJ"
                            ]</xpath>
                            <value>
                                <researchPrerequisite>CEH_45ColtFMJ_Research</researchPrerequisite>
                            </value>
                    </li>
    
                    <li Class="PatchOperationAdd">
                        <xpath>Defs/RecipeDef[
                            defName="MakeAmmo_3006Springfield_HP"
                            ]</xpath>
                            <value>
                                <researchPrerequisite>CEH_SemiAutomaticRifles_Research</researchPrerequisite>
                            </value>
                    </li>
                </operations>
            </match>
        </Operation>
    </Patch>